[
{"id": 1, "item": "Potion", "quantity": 0, "rate": 95, "ingredients": ["Herb", "Blue Mushroom"]},
{"id": 2, "item": "Mega Potion", "quantity": 0, "rate": 90, "ingredients": ["Potion", "Honey"]},
{"id": 3, "item": "Nutrients", "quantity": 0, "rate": 90, "ingredients": ["Blue Mushroom", "Godbug"]},
{"id": 4, "item": "Mega Nutrients", "quantity": 0, "rate": 75, "ingredients": ["Nutrients", "Honey"]},
{"id": 5, "item": "Antidote", "quantity": 0, "rate": 95, "ingredients": ["Antidote Herb", "Blue Mushroom"]},
{"id": 6, "item": "Herbal Medicine", "quantity": 0, "rate": 90, "ingredients": ["Cactus Flower", "Bitterbug"]},
{"id": 7, "item": "Max Potion", "quantity": 0, "rate": 65, "ingredients": ["Mega Nutrients", "Dragon Toadstool"]},
{"id": 8, "item": "Ancient Potion", "quantity": 0, "rate": 55, "ingredients": ["Immunizer", "Kelbi Horn"]},
{"id": 9, "item": "Catalyst", "quantity": 0, "rate": 75, "ingredients": ["Honey", "Bitterbug"]},
{"id": 10, "item": "Immunizer", "quantity": 0, "rate": 75, "ingredients": ["Catalyst", "Dragon Toadstool"]},
{"id": 11, "item": "Cleanser", "quantity": 0, "rate": 90, "ingredients": ["Catalyst", "Popfish"]},
{"id": 12, "item": "Dash Juice", "quantity": 0, "rate": 75, "ingredients": ["Catalyst", "Rare Steak"]},
{"id": 13, "item": "Mega Dash Juice", "quantity": 0, "rate": 65, "ingredients": ["Well-Done Steak", "Dash Extract"]},
{"id": 14, "item": "Energy Drink", "quantity": 0, "rate": 65, "ingredients": ["Honey", "Nitroshroom"]},
{"id": 15, "item": "Demondrug", "quantity": 0, "rate": 65, "ingredients": ["Catalyst", "Might Seed"]},
{"id": 16, "item": "Mega Demondrug", "quantity": 0, "rate": 55, "ingredients": ["Demondrug", "Pale Extract"]},
{"id": 17, "item": "Power Pill", "quantity": 0, "rate": 0, "ingredients": ["Immunizer", "Power Seed"]},
{"id": 18, "item": "Armorskin", "quantity": 0, "rate": 0, "ingredients": ["Catalyst", "Armor Seed"]},
{"id": 19, "item": "Mega Armorskin", "quantity": 0, "rate": 0, "ingredients": ["Armorskin", "Pale Extract"]},
{"id": 20, "item": "Armor Pill", "quantity": 0, "rate": 0, "ingredients": ["Immunizer", "Armor Seed"]},
{"id": 21, "item": "Hot Drink", "quantity": 0, "rate": 0, "ingredients": ["Fire Herb", "Bitterbug"]},
{"id": 22, "item": "Hot Meat", "quantity": 0, "rate": 0, "ingredients": ["Well-Done Steak", "Fire Herb"]},
{"id": 23, "item": "Cool Drink", "quantity": 0, "rate": 0, "ingredients": ["Ice Crystal", "Bitter Bug"]},
{"id": 24, "item": "Cold Meat", "quantity": 0, "rate": 0, "ingredients": ["Well-Done Steak", "Ice Crystal"]},
{"id": 25, "item": "Poisoned Meat", "quantity": 0, "rate": 0, "ingredients": ["Raw Meat", "Toadstool"]},
{"id": 26, "item": "Tainted Meat", "quantity": 0, "rate": 0, "ingredients": ["Raw Meat", "Parashroom"]},
{"id": 27, "item": "Drugged Meat", "quantity": 0, "rate": 0, "ingredients": ["Raw Meat", "Sleep Herb"]},
{"id": 28, "item": "Bomb Material", "quantity": 0, "rate": 0, "ingredients": ["Sap Plant", "Stone"]},
{"id": 29, "item": "Deodorant", "quantity": 0, "rate": 0, "ingredients": ["Bomb Material", "Ice Herb"]},
{"id": 30, "item": "Smoke Bomb", "quantity": 0, "rate": 0, "ingredients": ["Bomb Material", "Ivy"]},
{"id": 31, "item": "Poison S. Bomb", "quantity": 0, "rate": 0, "ingredients": ["Bomb Material", "Toadstool"]},
{"id": 32, "item": "Flash Bomb", "quantity": 0, "rate": 0, "ingredients": ["Bomb Material", "Flashbug"]},
{"id": 33, "item": "Dung Bomb", "quantity": 0, "rate": 0, "ingredients": ["Dung", "Bomb Material"]},
{"id": 34, "item": "Paintball", "quantity": 0, "rate": 0, "ingredients": ["Sap Plant", "Paintberry"]},
{"id": 35, "item": "Farcaster", "quantity": 0, "rate": 0, "ingredients": ["Bomb Material", "Exciteshroom"]},
{"id": 36, "item": "Gunpowder", "quantity": 0, "rate": 0, "ingredients": ["Fire Herb", "Nitroshroom"]},
{"id": 37, "item": "Sm. Barrel Bomb", "quantity": 0, "rate": 0, "ingredients": ["Small Barrel", "Fire Herb"]},
{"id": 38, "item": "Lg. Barrel Bomb", "quantity": 0, "rate": 0, "ingredients": ["Large Barrel", "Gunpowder"]},
{"id": 39, "item": "Lg. Barrel Bomb+", "quantity": 0, "rate": 0, "ingredients": ["Lg. Barrel Bomb", "Scatterfish"]},
{"id": 40, "item": "Bnc. Barrel Bomb", "quantity": 0, "rate": 0, "ingredients": ["Sm. Barrel Bomb", "Bnahabra Wing"]},
{"id": 41, "item": "Sonic Bomb", "quantity": 0, "rate": 0, "ingredients": ["Gunpowder", "Screamer"]},
{"id": 42, "item": "Felvine Bomb", "quantity": 0, "rate": 0, "ingredients": ["Sm. Barrel Bomb", "Felvine"]},
{"id": 43, "item": "Net", "quantity": 0, "rate": 0, "ingredients": ["Spiderweb", "Ivy"]},
{"id": 44, "item": "Pitfall Trap", "quantity": 0, "rate": 0, "ingredients": ["Net", "Trap Tool"]},
{"id": 45, "item": "Shock Trap", "quantity": 0, "rate": 0, "ingredients": ["Trap Tool", "Thunderbug"]},
{"id": 46, "item": "Goldenfish Bait", "quantity": 0, "rate": 0, "ingredients": ["Mega Fishing Fly", "Snakebee Larva"]},
{"id": 47, "item": "Baku Dango", "quantity": 0, "rate": 0, "ingredients": ["Mega Fishing Fly", "Bonhopper"]},
{"id": 48, "item": "Good Catch Dango", "quantity": 0, "rate": 0, "ingredients": ["Mega Fishing Fly", "Earbug"]},
{"id": 49, "item": "Old Pickaxe", "quantity": 0, "rate": 0, "ingredients": ["Stone", "Bone"]},
{"id": 50, "item": "Iron Pickaxe", "quantity": 0, "rate": 0, "ingredients": ["Iron Ore", "Bone"]},
{"id": 51, "item": "Mega Pickaxe", "quantity": 0, "rate": 0, "ingredients": ["Machalite Ore", "Bone"]},
{"id": 52, "item": "Old Bugnet", "quantity": 0, "rate": 0, "ingredients": ["Net", "Mystery Bone"]},
{"id": 53, "item": "Bugnet", "quantity": 0, "rate": 0, "ingredients": ["Net", "Sm. Monster B."]},
{"id": 54, "item": "Mega Bugnet", "quantity": 0, "rate": 0, "ingredients": ["Net", "Med. Monster B."]},
{"id": 55, "item": "Lifecrystal", "quantity": 0, "rate": 0, "ingredients": ["Godbug", "Wyvern Fang"]},
{"id": 56, "item": "Lifepowder", "quantity": 0, "rate": 0, "ingredients": ["Lifecrystal", "Wyvern Claw"]},
{"id": 57, "item": "Health Flute", "quantity": 0, "rate": 0, "ingredients": ["Lifepowder", "Flute"]},
{"id": 58, "item": "Antidote Flute", "quantity": 0, "rate": 0, "ingredients": ["Antidote", "Flute"]},
{"id": 59, "item": "Demon Flute", "quantity": 0, "rate": 0, "ingredients": ["Mega Demondrug", "Med. Monster B."]},
{"id": 60, "item": "Armor Flute", "quantity": 0, "rate": 0, "ingredients": ["Mega Armorskin", "Med. Monster B."]},
{"id": 61, "item": "Poison Thr. Knf", "quantity": 0, "rate": 0, "ingredients": ["Throwing Knife", "Toadstool"], "quest": true},
{"id": 62, "item": "Sleep Thr. Knf.", "quantity": 0, "rate": 0, "ingredients": ["Throwing Knife", "Sleep Herb"], "quest": true},
{"id": 63, "item": "Paralyze Thr. Knf.", "quantity": 0, "rate": 0, "ingredients": ["Throwing Knife", "Parashroom"], "quest": true},
{"id": 64, "item": "Boomerang", "quantity": 0, "rate": 0, "ingredients": ["Whetstone", "Sm. Monster B."]},
{"id": 65, "item": "Powertalon", "quantity": 0, "rate": 0, "ingredients": ["Powercharm", "Deviljho Talon"]},
{"id": 66, "item": "Armortalon", "quantity": 0, "rate": 0, "ingredients": ["Armorcharm", "Deviljho Talon"]},
{"id": 67, "item": "Normal S Lv2", "quantity": 0, "rate": 0, "ingredients": ["Huskberry", "Needleberry"]},
{"id": 68, "item": "Normal S Lv3", "quantity": 0, "rate": 0, "ingredients": ["Huskberry", "Rumblefish"]},
{"id": 69, "item": "Pierce S Lv1", "quantity": 0, "rate": 0, "ingredients": ["Huskberry", "Wolfsbane Berry"]},
{"id": 70, "item": "Pierce S Lv2", "quantity": 0, "rate": 0, "ingredients": ["Sm. Bone Husk", "B. Wywern Fang"]},
{"id": 71, "item": "Pierce S Lv3", "quantity": 0, "rate": 0, "ingredients": ["Sm. Bone Husk", "Pin Tuna"]},
{"id": 72, "item": "Pellet S Lv1", "quantity": 0, "rate": 0, "ingredients": ["Huskberry", "Scatternut"]},
{"id": 73, "item": "Pellet S Lv2", "quantity": 0, "rate": 0, "ingredients": ["Huskberry", "Wyvern Fang"]},
{"id": 74, "item": "Pellet S Lv3", "quantity": 0, "rate": 0, "ingredients": ["Sm. Bone Husk", "Wyvern Fang"]},
{"id": 75, "item": "Crag S Lv1", "quantity": 0, "rate": 0, "ingredients": ["Huskberry", "Nitroshroom"]},
{"id": 76, "item": "Crag S Lv2", "quantity": 0, "rate": 0, "ingredients": ["Sm. Bone Husk", "Burst Arrowana"]},
{"id": 77, "item": "Crag S Lv3", "quantity": 0, "rate": 0, "ingredients": ["Sm. Bone Husk", "Bomb Arrowana"]},
{"id": 78, "item": "Clust S Lv1", "quantity": 0, "rate": 0, "ingredients": ["Huskberry", "Bomberry"]},
{"id": 79, "item": "Clust S Lv2", "quantity": 0, "rate": 0, "ingredients": ["Sm. Bone Husk", "Wyvern Claw"]},
{"id": 80, "item": "Clust S Lv3", "quantity": 0, "rate": 0, "ingredients": ["Sm. Bone Husk", "Scatterfish"]},
{"id": 81, "item": "Flaming S", "quantity": 0, "rate": 0, "ingredients": ["Huskberry", "Fire Herb"]},
{"id": 82, "item": "Water S", "quantity": 0, "rate": 0, "ingredients": ["Huskberry", "Knife Mackarel"]},
{"id": 83, "item": "Freeze S", "quantity": 0, "rate": 0, "ingredients": ["Huskberry", "Ice Herb"]},
{"id": 84, "item": "Thunder S", "quantity": 0, "rate": 0, "ingredients": ["Huskberry", "Flashbug"]},
{"id": 85, "item": "Dragon S", "quantity": 0, "rate": 0, "ingredients": ["Sm. Bone Husk", "Dragon Seed"]},
{"id": 86, "item": "Recov S Lv1", "quantity": 0, "rate": 0, "ingredients": ["Huskberry", "Herb"]},
{"id": 87, "item": "Recov S Lv2", "quantity": 0, "rate": 0, "ingredients": ["Potion", "Huskberry"]},
{"id": 88, "item": "Poison S Lv1", "quantity": 0, "rate": 0, "ingredients": ["Huskberry", "Todstool"]},
{"id": 89, "item": "Poison S Lv2", "quantity": 0, "rate": 0, "ingredients": ["Sm. Bone Husk", "Furoggi Fang"]},
{"id": 90, "item": "Paralyze S Lv1", "quantity": 0, "rate": 0, "ingredients": ["Huskberry", "Parashroom"]},
{"id": 91, "item": "Paralyze S Lv2", "quantity": 0, "rate": 0, "ingredients": ["Sm. Bone Husk", "Bnahabra Claw"]},
{"id": 92, "item": "Sleep S Lv1", "quantity": 0, "rate": 0, "ingredients": ["Huskberry", "Sleep Herb"]},
{"id": 93, "item": "Sleep S Lv2", "quantity": 0, "rate": 0, "ingredients": ["Sm. Bone Husk", "Sllepyfish"]},
{"id": 94, "item": "Paint S", "quantity": 0, "rate": 0, "ingredients": ["Huskberry", "Paintberry"]},
{"id": 95, "item": "Demon S", "quantity": 0, "rate": 0, "ingredients": ["Demondrug", "Huskberry"]},
{"id": 96, "item": "Armor S", "quantity": 0, "rate": 0, "ingredients": ["Armorskin", "Huskberry"]},
{"id": 97, "item": "Exhaust S Lv1", "quantity": 0, "rate": 0, "ingredients": ["Huskberry", "Exhaustshroom"]},
{"id": 98, "item": "Exhaust S Lv2", "quantity": 0, "rate": 0, "ingredients": ["Sm. Bone Husk", "Exhaust Fish"]},
{"id": 99, "item": "Slicing S", "quantity": 0, "rate": 0, "ingredients": ["Whetstone", "Huskberry"]},
{"id": 100, "item": "Empty Bottle", "quantity": 0, "rate": 0, "ingredients": ["Whetstone", "Sm. Bone Husk"]},
{"id": 101, "item": "Poison Coating", "quantity": 0, "rate": 0, "ingredients": ["Empty Bottle", "Toadstool"]},
{"id": 102, "item": "Paralysis Coating", "quantity": 0, "rate": 0, "ingredients": ["Empty Bottle", "Parashroom"]},
{"id": 103, "item": "Sleep Coating", "quantity": 0, "rate": 0, "ingredients": ["Empty Bottle", "Sleep Herb"]},
{"id": 104, "item": "Power Coating", "quantity": 0, "rate": 0, "ingredients": ["Empty Bottle", "Nitroshroom"]},
{"id": 105, "item": "Close Range C.", "quantity": 0, "rate": 0, "ingredients": ["Empty Bottle", "Knife Mackarel"]},
{"id": 106, "item": "Paint Coating", "quantity": 0, "rate": 0, "ingredients": ["Empty Bottle", "Paintberry"]},
{"id": 107, "item": "Exhaust Coating", "quantity": 0, "rate": 0, "ingredients": ["Empty Bottle", "Exhaustshroom"]},
{"id": 108, "item": "Tranquilizer", "quantity": 0, "rate": 0, "ingredients": ["Sleep Herb", "Parashroom"]},
{"id": 109, "item": "Tranq. Thr. Knf.", "quantity": 0, "rate": 0, "ingredients": ["Tranquilizer", "Throwing Knife"], "quest": true},
{"id": 110, "item": "Tranq. Bomb", "quantity": 0, "rate": 0, "ingredients": ["Tranquilizer", "Bomb Material"]},
{"id": 111, "item": "Tranq. S", "quantity": 0, "rate": 0, "ingredients": ["Tranquilizer", "Husberry"]},
{"id": 112, "item": "Armor Sphere", "quantity": 0, "rate": 0, "ingredients": ["Machalite Ore", "Armor Stone"]},
{"id": 113, "item": "Armor Sphere", "quantity": 0, "rate": 0, "ingredients": ["Killer Beetle", "Armor Stone"]},
{"id": 114, "item": "Armor Sphere+", "quantity": 0, "rate": 0, "ingredients": ["Dragonite Ore", "Armor Stone"]},
{"id": 115, "item": "Armor Sphere+", "quantity": 0, "rate": 0, "ingredients": ["Hercudrome", "Armor Stone"]},
{"id": 116, "item": "Hrd. Armor Sphere", "quantity": 0, "rate": 0, "ingredients": ["Carbalite Ore", "Armor Stone"]},
{"id": 117, "item": "Hrd. Armor Sphere", "quantity": 0, "rate": 0, "ingredients": ["King Scarab", "Armor Stone"]}
]
